sysexecute/__init__.py
sysexecute/common.py
sysexecute/execute.py
sysexecute/networking.py
sysexecute-1.2.1.dist-info/LICENSE.txt
sysexecute-1.2.1.dist-info/METADATA
sysexecute-1.2.1.dist-info/WHEEL
sysexecute-1.2.1.dist-info/top_level.txt
sysexecute-1.2.1.dist-info/RECORD
