Metadata-Version: 2.1
Name: sysexecute
Version: 1.2.1
Summary: A library for simplified executing of system commands
Home-page: https://github.com/jasonfharris/sysexecute
Download-URL: https://github.com/jasonfharris/sysexecute/tarball/1.2.1
Author: Jason Harris
Author-email: jason@jasonfharris.com
License: MIT
Keywords: execute,shell,system
Classifier: Development Status :: 5 - Production/Stable
Classifier: Intended Audience :: Developers
Classifier: Topic :: Software Development
Classifier: Topic :: Software Development :: Libraries
Classifier: Topic :: Software Development :: Libraries :: Python Modules
Classifier: Topic :: System :: Networking
Classifier: Topic :: System :: Shells
Classifier: Topic :: System :: Systems Administration
Classifier: Topic :: Utilities
Classifier: License :: OSI Approved :: MIT License
Classifier: Programming Language :: Python :: 3.5
Classifier: Programming Language :: Python :: 3.6
Classifier: Programming Language :: Python :: 3.8
Classifier: Programming Language :: Python :: 3.9
Classifier: Programming Language :: Python :: 3.10
Classifier: Programming Language :: Python :: 3.11
License-File: LICENSE.txt
Requires-Dist: argcomplete
